sentry_plugin_ph/__init__.py
sentry_plugin_ph/forms.py
sentry_plugin_ph/plugin.py
sentry_plugin_ph/template.py
sentry_plugin_ph-0.0.10.dist-info/LICENSE
sentry_plugin_ph-0.0.10.dist-info/METADATA
sentry_plugin_ph-0.0.10.dist-info/WHEEL
sentry_plugin_ph-0.0.10.dist-info/entry_points.txt
sentry_plugin_ph-0.0.10.dist-info/top_level.txt
sentry_plugin_ph-0.0.10.dist-info/RECORD
