Metadata-Version: 2.1
Name: sentry-plugin-ph
Version: 0.0.10
Summary: ph notification plugin for Sentry
Author: p
Classifier: Programming Language :: Python :: 3.8
Classifier: License :: OSI Approved :: MIT License
Classifier: Operating System :: OS Independent
Requires-Python: >=3.8
License-File: LICENSE
Requires-Dist: sentry>=9.0.0
Requires-Dist: markdown>=3.0.0
